SBDL/__init__.py
SBDL/__main__.py
SBDL/definitions.py
SBDL/main_sbdl.py
SBDL/run_sbdl.py
SBDL/lib/__init__.py
SBDL/lib/configLoader.py
SBDL/lib/logger.py
SBDL/lib/utils.py
SBDL/resource/config/log4j.properties
SBDL/resource/config/sbdl.conf
SBDL/resource/config/spark.conf
SBDL/resource/sql/read_employee.sql
SBDL/scripts/__init__.py
SBDL/scripts/run_databricks.py
SBDL/src/__init__.py
SBDL/src/core/__init__.py
SBDL/src/core/entity.py
SBDL/src/core/publisher.py
SBDL/src/core/registry.py
SBDL/src/core/source.py
SBDL/src/core/target.py
SBDL/src/entity/__init__.py
SBDL/src/entity/acctload.py
SBDL/src/entity/custload.py
sbdletldemo-0.0.6.dist-info/METADATA
sbdletldemo-0.0.6.dist-info/WHEEL
sbdletldemo-0.0.6.dist-info/entry_points.txt
sbdletldemo-0.0.6.dist-info/top_level.txt
sbdletldemo-0.0.6.dist-info/RECORD
