Metadata-Version: 2.1
Name: sbdletldemo
Version: 0.0.6
Summary: Package of SBDL app
Author: Aakash Verma
Author-email: akash967049@gmail.com
Keywords: python,etl,boiler,local,databricks
